improutils/__init__.py
improutils/other.py
improutils/acquisition/__init__.py
improutils/acquisition/img_io.py
improutils/acquisition/io.py
improutils/acquisition/pypylon.py
improutils/acquisition/pypylon_config.py
improutils/filtration/__init__.py
improutils/filtration/filtration.py
improutils/preprocessing/__init__.py
improutils/preprocessing/contours.py
improutils/preprocessing/preprocessing.py
improutils/recognition/__init__.py
improutils/recognition/image_features.py
improutils/recognition/ocr.py
improutils/segmentation/__init__.py
improutils/segmentation/segmentation.py
improutils/visualisation/__init__.py
improutils/visualisation/visualisation.py
improutils-0.1.1.dist-info/LICENCE
improutils-0.1.1.dist-info/METADATA
improutils-0.1.1.dist-info/WHEEL
improutils-0.1.1.dist-info/top_level.txt
improutils-0.1.1.dist-info/RECORD
