Metadata-Version: 2.1
Name: improutils
Version: 0.1.1
Summary: Package with useful functions for BI-SVZ coursework
Home-page: https://github.com/ImprolabFIT/improutils_package
Author: ImproLab
Author-email: improlab@fit.cvut.cz
License: UNKNOWN
Platform: UNKNOWN
Classifier: Programming Language :: Python :: 3
Classifier: License :: OSI Approved :: MIT License
Classifier: Operating System :: OS Independent
Requires-Python: >=3.6
